fishlifeseq.cpython-39-x86_64-linux-gnu.so
runshell.cpython-39-x86_64-linux-gnu.so
fishlifeqc/__init__.py
fishlifeqc/bl.py
fishlifeqc/boldsearch.py
fishlifeqc/concatenate.py
fishlifeqc/core_fishlife.py
fishlifeqc/delete.py
fishlifeqc/missingdata.py
fishlifeqc/monophyly.py
fishlifeqc/pairedblast.py
fishlifeqc/symtests.py
fishlifeqc/t_like.py
fishlifeqc/utils.py
fishlifeqc-1.2.5.data/data/bin/blastn_Linux_64bit
fishlifeqc-1.2.5.data/data/bin/catpv
fishlifeqc-1.2.5.data/data/bin/consel
fishlifeqc-1.2.5.data/data/bin/makeblastdb_Linux_64bit
fishlifeqc-1.2.5.data/data/bin/makermt
fishlifeqc-1.2.5.data/data/bin/raxmlHPC-PTHREADS-SSE3_Linux_64bit
fishlifeqc-1.2.5.data/data/bin/seqmt
fishlifeqc-1.2.5.data/scripts/codon_partition.py
fishlifeqc-1.2.5.data/scripts/collapse.py
fishlifeqc-1.2.5.data/scripts/concatenate.py
fishlifeqc-1.2.5.data/scripts/cons_trees.py
fishlifeqc-1.2.5.data/scripts/merge.py
fishlifeqc-1.2.5.data/scripts/splitexonfiles.py
qcutil/__init__.py
qcutil/cli.py
qcutil/summarize.py
fishlifeqc-1.2.5.dist-info/LICENSE
fishlifeqc-1.2.5.dist-info/METADATA
fishlifeqc-1.2.5.dist-info/WHEEL
fishlifeqc-1.2.5.dist-info/entry_points.txt
fishlifeqc-1.2.5.dist-info/top_level.txt
fishlifeqc-1.2.5.dist-info/RECORD
